Makefile
README.rst
setup.py
docs/Makefile
docs/make.bat
docs/source/HISTORY.rst
docs/source/README.rst
docs/source/api.rst
docs/source/conf.py
docs/source/index.rst
scripts/api-sample.py
scripts/out.txt
scripts/sample.zip
xmldirector/__init__.py
xmldirector.crex.egg-info/PKG-INFO
xmldirector.crex.egg-info/SOURCES.txt
xmldirector.crex.egg-info/dependency_links.txt
xmldirector.crex.egg-info/entry_points.txt
xmldirector.crex.egg-info/namespace_packages.txt
xmldirector.crex.egg-info/not-zip-safe
xmldirector.crex.egg-info/requires.txt
xmldirector.crex.egg-info/top_level.txt
xmldirector/crex/__init__.py
xmldirector/crex/configure.zcml
xmldirector/crex/header.txt
xmldirector/crex/i18n.py
xmldirector/crex/interfaces.py
xmldirector/crex/logger.py
xmldirector/crex/browser/__init__.py
xmldirector/crex/browser/api-sample.py
xmldirector/crex/browser/configure.zcml
xmldirector/crex/browser/controlpanel.py
xmldirector/crex/browser/crex.pt
xmldirector/crex/browser/queue.py
xmldirector/crex/browser/restapi.py
xmldirector/crex/browser/rewriterules.py
xmldirector/crex/browser/view.py
xmldirector/crex/browser/data/sample.docx
xmldirector/crex/browser/data/sample.zip
xmldirector/crex/locales/LC_MESSAGES/de/README.txt
xmldirector/crex/profiles/default/README.txt
xmldirector/crex/profiles/default/browserlayer.xml
xmldirector/crex/profiles/default/controlpanel.xml
xmldirector/crex/profiles/default/metadata.xml
xmldirector/crex/profiles/default/registry.xml
xmldirector/crex/profiles/default/types.xml
xmldirector/crex/profiles/default/types/xmldirector.plonecore.connector.xml