Metadata-Version: 1.1
Name: xmldirector.crex
Version: 0.3.0
Summary: Plone/XML-Director integration with c-rex.net
Home-page: http://pypi.python.org/pypi/xmldirector.crex
Author: Andreas Jung
Author-email: info@zopyx.com
License: GPL
Keywords: xml-director DOCX XML C-Rex Plone Python
Platform: UNKNOWN
Classifier: Programming Language :: Python
Classifier: Framework :: Plone
Classifier: Framework :: Plone :: 4.3
Classifier: Framework :: Plone :: 5.0
Classifier: Framework :: Zope2
Classifier: Topic :: Software Development :: Libraries :: Python Modules
